mcrnmf/__init__.py
mcrnmf/_utils.py
mcrnmf/models.py
mcrnmf/nnls.py
mcrnmf/datasets/__init__.py
mcrnmf/datasets/_loaders.py
mcrnmf/datasets/raman.csv
mcrnmf/tests/__init__.py
mcrnmf/tests/models_test.py
mcrnmf/tests/nnls_test.py
mcrnmf-0.1.0.dist-info/licenses/LICENSE
mcrnmf-0.1.0.dist-info/METADATA
mcrnmf-0.1.0.dist-info/WHEEL
mcrnmf-0.1.0.dist-info/top_level.txt
mcrnmf-0.1.0.dist-info/RECORD
