Metadata-Version: 2.4
Name: mcrnmf
Version: 0.1.0
Summary: Multivariate Curve Resolution using Nonnegative Matrix Factorization
Author-email: "Siddarth A. Vasudevan" <devan.siddarth@gmail.com>
License-Expression: MIT
Project-URL: Homepage, https://siddarthvasudevan.github.io/mcrnmf/
Project-URL: Repository, https://github.com/siddarthVasudevan/mcrnmf
Keywords: MCR,chemometrics,NMF,Multivariate Curve Resolution,Nonnegative Matrix Factorization
Classifier: Programming Language :: Python :: 3.11
Classifier: Operating System :: OS Independent
Requires-Python: <3.14,>=3.11.9
License-File: LICENSE
Requires-Dist: numba>=0.61.2
Requires-Dist: numpy<2.3,>=1.24
Dynamic: license-file
